mqttclient/__init__.py
mqttclient/mqtt_messages.py
mqttclient-0.0.2.dist-info/LICENSE
mqttclient-0.0.2.dist-info/WHEEL
mqttclient-0.0.2.dist-info/METADATA
mqttclient-0.0.2.dist-info/RECORD
