Metadata-Version: 1.1
Name: mqttclient
Version: 0.0.2
Summary: MQTT Client for Python
Home-page: https://github.com/Lucaszw/mqttclient-python
Author: Sci-Bots
Author-email: lucas@sci-bots.com
